mindgraph/__init__.py
mindgraph/graph/BaseGraphBackend.py
mindgraph/graph/GraphBackend.py
mindgraph/graph/GraphBackendInterface.py
mindgraph/graph/NetworkXGraphBackend.py
mindgraph/graph/SimpleGraphBackend.py
mindgraph/graph/__init__.py
mindgraph/graph/exceptions.py
mindgraph/graph/operations_on_facts/__init__.py
mindgraph/graph/operations_on_facts/convert_facts_to_abstract_graph.py
mindgraph/graph/operations_on_facts/convert_facts_to_dataframe.py
mindgraph/graph/operations_on_facts/filter_facts.py
mindgraph/graph/operations_on_facts/validate_facts_format.py
mindgraph/utils/dir.py
mindgraph-2025.3.1.1.dist-info/licenses/LICENSE
mindgraph-2025.3.1.1.dist-info/WHEEL
mindgraph-2025.3.1.1.dist-info/METADATA
mindgraph-2025.3.1.1.dist-info/RECORD
