Metadata-Version: 2.4
Name: mindgraph
Version: 2025.3.1.1
Summary: Mindgraph: A Python package for modeling knowledge as graphs.
Author-email: Idin K <python@idin.net>
License-File: LICENSE
Project-URL: Home, https://github.com/idin/mindgraph
